easyfix/__init__.py
easyfix-0.1.3.dist-info/LICENSE
easyfix-0.1.3.dist-info/METADATA
easyfix-0.1.3.dist-info/WHEEL
easyfix-0.1.3.dist-info/top_level.txt
easyfix-0.1.3.dist-info/RECORD
