Metadata-Version: 2.1
Name: easyfix
Version: 0.1.3
Summary: UNKNOWN
Home-page: https://github.com/kizzx2/easyfix
Author: Chris Yuen
Author-email: chris@kizzx2.com
License: UNKNOWN
Platform: UNKNOWN
Requires-Dist: lxml
Requires-Dist: loguru
